LICENSE
MANIFEST.in
Readme.md
ramex
ramex.py
setup.cfg
setup.py
Ramex.egg-info/PKG-INFO
Ramex.egg-info/SOURCES.txt
Ramex.egg-info/dependency_links.txt
Ramex.egg-info/requires.txt
Ramex.egg-info/top_level.txt
files/__init__.py
files/requirements.txt