Metadata-Version: 2.1
Name: Ramex
Version: 0.1
Summary: Ultimate Member Adding Tool for Telegram
Author: @Annex_xD
License: GPLv3
License-File: LICENSE
